metadata/__init__.py
museopheno/__init__.py
museopheno/datasets/2018_3A_Theia_Bouconne.tif
museopheno/datasets/__init__.py
museopheno/sensors/__computeS2SITS.py
museopheno/sensors/__init__.py
museopheno/time_series/__dl.py
museopheno/time_series/__init__.py
museopheno-0.1rc1.dist-info/METADATA
museopheno-0.1rc1.dist-info/WHEEL
museopheno-0.1rc1.dist-info/top_level.txt
museopheno-0.1rc1.dist-info/RECORD
