Metadata-Version: 2.1
Name: museopheno
Version: 0.1rc1
Summary: Time series and spectral indice management for Remote Sensing Sensors
Home-page: https://github.com/nkarasiak/MuseoPheno
Author: Nicolas Karasiak
Author-email: karasiak.nicolas@gmail.com
License: GPLv3
Platform: UNKNOWN
Classifier: Topic :: Scientific/Engineering :: Artificial Intelligence
Classifier: Topic :: Scientific/Engineering :: GIS
Classifier: Programming Language :: Python :: 3
Classifier: Intended Audience :: Science/Research
Requires-Dist: numpy
Requires-Dist: scipy
Requires-Dist: matplotlib
Requires-Dist: scikit-learn
Requires-Dist: joblib
Requires-Dist: museotoolbox
